llama_scan/__init__.py
llama_scan/cli.py
llama_scan/constants.py
llama_scan/ollama.py
llama_scan/processor.py
llama_scan/utils.py
llama_scan-0.1.8.dist-info/METADATA
llama_scan-0.1.8.dist-info/WHEEL
llama_scan-0.1.8.dist-info/entry_points.txt
llama_scan-0.1.8.dist-info/licenses/LICENSE.txt
llama_scan-0.1.8.dist-info/RECORD
