Metadata-Version: 2.4
Name: llama-scan
Version: 0.1.8
Summary: A tool for converting PDFs to text files using Ollama.
Project-URL: Homepage, https://github.com/ngafar/llama-scan
Project-URL: Issues, https://github.com/ngafar/llama-scan/issues
License-File: LICENSE.txt
Requires-Python: >=3.10
Requires-Dist: pillow>=11.2.1
Requires-Dist: pymupdf>=1.26.1
Requires-Dist: requests>=2.32.4
Requires-Dist: tqdm>=4.67.1
